lab_overrides/create_dataframe.py
lab_overrides/dal/__init__.py
lab_overrides/dal/connect_db.py
lab_overrides/display_dataset.py
lab_overrides/featureextraction/__init__.py
lab_overrides/featureextraction/featureextraction.py
lab_overrides/infer/__init__.py
lab_overrides/infer/infer.py
lab_overrides/infer.py
lab_overrides-0.1.8.dist-info/entry_points.txt
lab_overrides-0.1.8.dist-info/WHEEL
lab_overrides-0.1.8.dist-info/METADATA
lab_overrides-0.1.8.dist-info/RECORD
