Metadata-Version: 2.1
Name: lab-overrides
Version: 0.1.8
Summary: 
Author: Tova Hallas
Author-email: tova.hallas@igentify.com
Requires-Python: >=3.6.9,<4.0.0
Classifier: Programming Language :: Python :: 3
Classifier: Programming Language :: Python :: 3.7
Classifier: Programming Language :: Python :: 3.8
Classifier: Programming Language :: Python :: 3.9
Requires-Dist: matplotlib (==3.3.4)
Requires-Dist: pandas (==1.1.4)
Requires-Dist: pickle5 (>=0.0.11,<0.0.12)
Requires-Dist: psycopg2 (==2.7)
Requires-Dist: sklearn (>=0.0,<0.1)
Requires-Dist: tensorflow (==2.4.1)
